randgenlib/__init__.py
randgenlib-1.0.4.dist-info/METADATA
randgenlib-1.0.4.dist-info/WHEEL
randgenlib-1.0.4.dist-info/top_level.txt
randgenlib-1.0.4.dist-info/RECORD
