Metadata-Version: 2.1
Name: randgenlib
Version: 1.0.4
Summary: Random generation lib
Home-page: UNKNOWN
Author: GigaAlex
Author-email: nick.faltermeier@gmx.de
License: UNKNOWN
Keywords: python
Platform: UNKNOWN
Classifier: Operating System :: Microsoft :: Windows
